Apimatic/__init__.py
Apimatic/__main__.py
Apimatic/cli.py
Apimatic/detect.py
Apimatic/generator.py
Apimatic/utils.py
Apimatic/parsers/__init__.py
Apimatic/parsers/django.py
Apimatic/parsers/express.py
Apimatic/parsers/fastapi.py
Apimatic/parsers/flask.py
Apimatic/usedAllAI/googleGemini.py
Apimatic/usedAllAI/groq.py
Apimatic/usedAllAI/ollama.py
Apimatic/usedAllAI/openAI.py
apimatic-0.1.8.dist-info/licenses/LICENSE
apimatic-0.1.8.dist-info/METADATA
apimatic-0.1.8.dist-info/WHEEL
apimatic-0.1.8.dist-info/entry_points.txt
apimatic-0.1.8.dist-info/top_level.txt
apimatic-0.1.8.dist-info/RECORD
