Metadata-Version: 2.4
Name: Apimatic
Version: 0.1.8
Summary: Universal API documentation generator
Author-email: Matrixxboy <matrix.utsav.lankapati@gmail.com>
Requires-Python: >=3.9
License-File: LICENSE
Requires-Dist: pyyaml
Requires-Dist: openai
Requires-Dist: google-generativeai
Requires-Dist: groq
Dynamic: license-file
